dummy_pkg/_init_.py
rocm_sdk_libraries_gfx1151-0.0.1.dist-info/METADATA
rocm_sdk_libraries_gfx1151-0.0.1.dist-info/WHEEL
rocm_sdk_libraries_gfx1151-0.0.1.dist-info/top_level.txt
rocm_sdk_libraries_gfx1151-0.0.1.dist-info/RECORD
