Metadata-Version: 2.4
Name: rocm-sdk-libraries-gfx1151
Version: 0.0.1
Summary: rocm-sdk-libraries-gfx1151 PyPI uploads
Author-email: Shiraz <sali@amd.com>
License: MIT
Project-URL: Homepage, https://rocm.nightlies.amd.com/v2/gfx1151/
Requires-Python: >=3.8
